prometh_cortex/__init__.py
prometh_cortex/analyzer/__init__.py
prometh_cortex/analyzer/analyzer.py
prometh_cortex/analyzer/metrics.py
prometh_cortex/analyzer/recommender.py
prometh_cortex/cli/__init__.py
prometh_cortex/cli/animations.py
prometh_cortex/cli/main.py
prometh_cortex/cli/commands/__init__.py
prometh_cortex/cli/commands/analyze.py
prometh_cortex/cli/commands/build.py
prometh_cortex/cli/commands/fields.py
prometh_cortex/cli/commands/health.py
prometh_cortex/cli/commands/mcp.py
prometh_cortex/cli/commands/mcp_generators.py
prometh_cortex/cli/commands/query.py
prometh_cortex/cli/commands/rebuild.py
prometh_cortex/cli/commands/serve.py
prometh_cortex/cli/commands/sources.py
prometh_cortex/config/__init__.py
prometh_cortex/config/settings.py
prometh_cortex/indexer/__init__.py
prometh_cortex/indexer/document_indexer.py
prometh_cortex/indexer/document_indexer_old.py
prometh_cortex/mcp/__init__.py
prometh_cortex/mcp/enhanced_tools.py
prometh_cortex/mcp/server.py
prometh_cortex/mcp/timeout_handler.py
prometh_cortex/parser/__init__.py
prometh_cortex/parser/frontmatter.py
prometh_cortex/parser/markdown.py
prometh_cortex/parser/query_parser.py
prometh_cortex/router/__init__.py
prometh_cortex/server/__init__.py
prometh_cortex/server/app.py
prometh_cortex/utils/__init__.py
prometh_cortex/vector_store/__init__.py
prometh_cortex/vector_store/change_detector.py
prometh_cortex/vector_store/factory.py
prometh_cortex/vector_store/faiss_store.py
prometh_cortex/vector_store/interface.py
prometh_cortex/vector_store/qdrant_store.py
prometh_cortex-0.3.0.dist-info/METADATA
prometh_cortex-0.3.0.dist-info/WHEEL
prometh_cortex-0.3.0.dist-info/entry_points.txt
prometh_cortex-0.3.0.dist-info/licenses/LICENSE
prometh_cortex-0.3.0.dist-info/licenses/NOTICE
prometh_cortex-0.3.0.dist-info/RECORD
