Metadata-Version: 2.4
Name: prometh-cortex
Version: 0.3.0
Summary: Multi-Datalake RAG Indexer with Unified Collection & Per-Source Chunking - MCP & HTTP Server
Project-URL: Homepage, https://github.com/ivannagy/prometh-cortex
Project-URL: Repository, https://github.com/ivannagy/prometh-cortex.git
Project-URL: Issues, https://github.com/ivannagy/prometh-cortex/issues
Author-email: Ivan Nagy <prometh-cortex@prometh.sh>
License:                                  Apache License
License-File: LICENSE
License-File: NOTICE
Classifier: Development Status :: 3 - Alpha
Classifier: Intended Audience :: Developers
Classifier: License :: OSI Approved :: Apache Software License
Classifier: Programming Language :: Python :: 3
Classifier: Programming Language :: Python :: 3.10
Classifier: Programming Language :: Python :: 3.11
Classifier: Programming Language :: Python :: 3.12
Requires-Python: >=3.10
Requires-Dist: click>=8.0.0
Requires-Dist: faiss-cpu>=1.7.0
Requires-Dist: fastapi>=0.100.0
Requires-Dist: fastmcp>=0.9.0
Requires-Dist: llama-index-embeddings-huggingface>=0.1.0
Requires-Dist: llama-index-vector-stores-faiss>=0.1.0
Requires-Dist: llama-index>=0.10.0
Requires-Dist: markdown>=3.4.0
Requires-Dist: pydantic>=2.0.0
Requires-Dist: python-frontmatter>=1.0.0
Requires-Dist: pyyaml>=6.0.0
Requires-Dist: qdrant-client>=1.7.0
Requires-Dist: rich>=13.0.0
Requires-Dist: sentence-transformers>=2.2.0
Requires-Dist: toml>=0.10.0
Requires-Dist: tqdm>=4.65.0
Requires-Dist: uvicorn[standard]>=0.23.0
Provides-Extra: dev
Requires-Dist: black>=23.0.0; extra == 'dev'
Requires-Dist: flake8>=6.0.0; extra == 'dev'
Requires-Dist: isort>=5.12.0; extra == 'dev'
Requires-Dist: mypy>=1.5.0; extra == 'dev'
Requires-Dist: pre-commit>=3.0.0; extra == 'dev'
Requires-Dist: pytest-asyncio>=0.21.0; extra == 'dev'
Requires-Dist: pytest-cov>=4.0.0; extra == 'dev'
Requires-Dist: pytest>=7.0.0; extra == 'dev'
